datacatalogtordf/__init__.py
datacatalogtordf/agent.py
datacatalogtordf/catalog.py
datacatalogtordf/catalogrecord.py
datacatalogtordf/contact.py
datacatalogtordf/dataservice.py
datacatalogtordf/dataset.py
datacatalogtordf/dataset_series.py
datacatalogtordf/distribution.py
datacatalogtordf/document.py
datacatalogtordf/exceptions.py
datacatalogtordf/location.py
datacatalogtordf/periodoftime.py
datacatalogtordf/relationship.py
datacatalogtordf/resource.py
datacatalogtordf/uri.py
datacatalogtordf-4.0.0.dist-info/LICENSE
datacatalogtordf-4.0.0.dist-info/METADATA
datacatalogtordf-4.0.0.dist-info/WHEEL
datacatalogtordf-4.0.0.dist-info/RECORD
