Metadata-Version: 2.1
Name: datacatalogtordf
Version: 4.0.0
Summary: A library for mapping a data catalog to rdf
Home-page: https://github.com/Informasjonsforvaltning/datacatalogtordf
License: Apache-2.0
Author: Stig B. Dørmænen
Author-email: stigbd@gmail.com
Requires-Python: >=3.10,<3.13
Classifier: License :: OSI Approved :: Apache Software License
Classifier: Operating System :: OS Independent
Classifier: Programming Language :: Python :: 3
Classifier: Programming Language :: Python :: 3.10
Classifier: Programming Language :: Python :: 3.11
Classifier: Programming Language :: Python :: 3.12
Requires-Dist: rdflib (>=7.0.0,<8.0.0)
Requires-Dist: skolemizer (>=1.1.0,<2.0.0)
Project-URL: Documentation, https://datacatalogtordf.readthedocs.io
Project-URL: Repository, https://github.com/Informasjonsforvaltning/datacatalogtordf
